pysips/__init__.py
pysips/crossover_proposal.py
pysips/laplace_nmll.py
pysips/metropolis.py
pysips/mutation_proposal.py
pysips/prior.py
pysips/random_choice_proposal.py
pysips/regressor.py
pysips/sampler.py
pysips-0.2.0.dist-info/licenses/LICENSE
tests/integration/test_log_likelihood.py
tests/integration/test_prior_with_bingo.py
tests/regression/test_basic_end_to_end.py
tests/regression/test_regressor_end_to_end.py
tests/unit/test_crossover_proposal.py
tests/unit/test_laplace_nmll.py
tests/unit/test_metropolis.py
tests/unit/test_mutation_proposal.py
tests/unit/test_prior.py
tests/unit/test_random_choice_proposal.py
tests/unit/test_regressor.py
tests/unit/test_sampler.py
pysips-0.2.0.dist-info/METADATA
pysips-0.2.0.dist-info/WHEEL
pysips-0.2.0.dist-info/top_level.txt
pysips-0.2.0.dist-info/RECORD
