Metadata-Version: 2.4
Name: pysips
Version: 0.2.0
Summary: A python package for symbolic inference via posterior sampling.
Author-email: Geoffrey Bomarito <geoffrey.f.bomarito@nasa.gov>, Patrick Leser <patrick.e.leser@nasa.gov>
License-Expression: NASA-1.3
Project-URL: Documentation, https://nasa.github.io/pysips/
Project-URL: Repository, https://github.com/nasa/pysips
Keywords: symbolic regression
Classifier: Development Status :: 3 - Alpha
Classifier: Programming Language :: Python :: 3.12
Classifier: Programming Language :: Python :: 3.13
Requires-Python: >=3.10
License-File: LICENSE
Requires-Dist: numpy
Requires-Dist: bingo-nasa
Requires-Dist: smcpy>=0.1.11
Requires-Dist: scikit-learn
Dynamic: license-file
